CHANGES.txt
README.txt
setup.py
collective/__init__.py
collective.local.deploygroup.egg-info/PKG-INFO
collective.local.deploygroup.egg-info/SOURCES.txt
collective.local.deploygroup.egg-info/dependency_links.txt
collective.local.deploygroup.egg-info/entry_points.txt
collective.local.deploygroup.egg-info/namespace_packages.txt
collective.local.deploygroup.egg-info/not-zip-safe
collective.local.deploygroup.egg-info/requires.txt
collective.local.deploygroup.egg-info/top_level.txt
collective/local/__init__.py
collective/local/deploygroup/__init__.py
collective/local/deploygroup/configure.zcml
collective/local/deploygroup/browser/__init__.py
collective/local/deploygroup/browser/configure.zcml
collective/local/deploygroup/browser/deploygroup_macro_wrapper.pt
collective/local/deploygroup/browser/sharing.pt
collective/local/deploygroup/browser/sharing.py
collective/local/deploygroup/locales/deploygroup.pot
collective/local/deploygroup/locales/update.sh
collective/local/deploygroup/locales/fr/LC_MESSAGES/deploygroup.po