Metadata-Version: 1.0
Name: collective.local.deploygroup
Version: 1.0
Summary: Allows to deploy a group from the sharing view. By Ecreall
Home-page: http://svn.plone.org/svn/collective/collective.local.deploygroup
Author: Vincent Fretin
Author-email: vincent.fretin@gmail.com
License: GPL
Platform: UNKNOWN
Classifier: Framework :: Plone
Classifier: Programming Language :: Python
